{
    "mysteryDungeon:ExplorersDeck": {
        "NAME": "冒险家牌组",
        "DESCRIPTION": "一旦你选择了冒险家，将获得5张牌。"
    },
    "mysteryDungeon:PartnersDeck": {
        "NAME": "伙伴牌组",
        "DESCRIPTION": "一旦你选择了伙伴，将获得5张牌。"
    },
    "mysteryDungeon:ColorlessAgility": {
        "NAME": "高速移动",
        "DESCRIPTION": "保留。 NL 抽 !M! 张牌。 NL 消耗。"
    },
    "mysteryDungeon:ChooseAttack": {
        "NAME": "攻击",
        "DESCRIPTION": "向手牌添加一张随机攻击牌。"
    },
    "mysteryDungeon:ChooseNegative": {
        "NAME": "负极态",
        "DESCRIPTION": "进入 mysterydungeon:负极态 。"
    },
    "mysteryDungeon:ChoosePositive": {
        "NAME": "正极态",
        "DESCRIPTION": "进入 mysterydungeon:正极态 。"
    },
    "mysteryDungeon:ChooseSkill": {
        "NAME": "技能",
        "DESCRIPTION": "向手牌添加一张随机技能牌。"
    },
    "mysteryDungeon:StatusFreeze": {
        "NAME": "冷冻",
        "DESCRIPTION": "保留。"
    },
    "mysteryDungeon:BulbasaurBulletSeed": {
        "NAME": "种子机关枪",
        "DESCRIPTION": "造成 !D! 点伤害 !M! 次。 NL 可多次升级。"
    },
    "mysteryDungeon:BulbasaurChlorophyll": {
        "NAME": "叶绿素",
        "DESCRIPTION": "抽 !M! 张牌。 NL 若抽到一张攻击牌，获得1点力量。",
        "UPGRADE_DESCRIPTION": "抽 !M! 张牌。 NL 每抽到一张攻击牌，获得1点力量。"
    },
    "mysteryDungeon:BulbasaurDefend": {
        "NAME": "防御",
        "DESCRIPTION": "获得 !B! 点 格挡 。"
    },
    "mysteryDungeon:BulbasaurDefenseCurl": {
        "NAME": "变圆",
        "DESCRIPTION": "获得 !B! 点 格挡 。"
    },
    "mysteryDungeon:BulbasaurDoubleEdge": {
        "NAME": "双刃",
        "DESCRIPTION": "造成 !D! 点伤害。 NL 获得等同于未 格挡 伤害的力量。 NL 消耗。",
        "UPGRADE_DESCRIPTION": "造成 !D! 点伤害 !M! 次。 NL 获得等同于未 格挡 伤害的力量。 NL 消耗。"
    },
    "mysteryDungeon:BulbasaurExplorerForm": {
        "NAME": "妙蛙种子·冒险者笔记",
        "DESCRIPTION": "获得 !M! 层回复。 NL 在回合开始时，失去1点 敏捷 。"
    },
    "mysteryDungeon:BulbasaurFrenzyPlant": {
        "NAME": "疯狂植物",
        "DESCRIPTION": "造成 !D! 点伤害 !M! 次。 NL 施加2层中毒 !M! 次。 NL 本回合无法回复生命。"
    },
    "mysteryDungeon:BulbasaurGigaDrain": {
        "NAME": "终极吸收",
        "DESCRIPTION": "虚无。 NL 造成 !D! 点伤害。 NL 回复等同于未 格挡 伤害的生命。"
    },
    "mysteryDungeon:BulbasaurGrowl": {
        "NAME": "叫声",
        "DESCRIPTION": "对所有敌人施加 !M! 层 虚弱 。"
    },
    "mysteryDungeon:BulbasaurGrowth": {
        "NAME": "生长",
        "DESCRIPTION": "获得 !M! 点力量。"
    },
    "mysteryDungeon:BulbasaurIngrain": {
        "NAME": "扎根",
        "DESCRIPTION": "向随机敌人施加1层 mysterydungeon:寄生种子  !M! 次。 NL 失去2点 敏捷 。 NL 消耗。"
    },
    "mysteryDungeon:BulbasaurLeechSeed": {
        "NAME": "寄生种子",
        "DESCRIPTION": "施加 !M! 层 mysterydungeon:寄生种子 。 NL 消耗。"
    },
    "mysteryDungeon:BulbasaurMegaDrain": {
        "NAME": "超级吸收",
        "DESCRIPTION": "敌人每拥有1种减益效果，回复 !M! 生命值。",
        "UPGRADE_DESCRIPTION": "敌人每拥有1种减益效果，回复 !M! 生命值。 NL 下回合多抽1张牌。"
    },
    "mysteryDungeon:BulbasaurPetalBlizzard": {
        "NAME": "落英缤纷",
        "DESCRIPTION": "对所有敌人造成 !D! 点伤害。"
    },
    "mysteryDungeon:BulbasaurPetalDance": {
        "NAME": "花瓣舞",
        "DESCRIPTION": "下 !M! 回合，在回合结束时，对所有敌人造成7点伤害。 NL 视为攻击伤害。"
    },
    "mysteryDungeon:BulbasaurPoisonJab": {
        "NAME": "毒击",
        "DESCRIPTION": "造成 !D! 点伤害。 NL 施加 !M! 层中毒2次。"
    },
    "mysteryDungeon:BulbasaurPoisonPoint": {
        "NAME": "毒刺",
        "DESCRIPTION": "获得 !M! 层 mysterydungeon:毒刺 。"
    },
    "mysteryDungeon:BulbasaurPoisonPowder": {
        "NAME": "毒粉",
        "DESCRIPTION": "对所有敌人施加 !M! 层中毒。"
    },
    "mysteryDungeon:BulbasaurPowerWhip": {
        "NAME": "强力鞭打",
        "DESCRIPTION": "保留。 NL 造成 !D! 点伤害。"
    },
    "mysteryDungeon:BulbasaurProtect": {
        "NAME": "守住",
        "DESCRIPTION": "获得 !B! 点 格挡 。 NL 下 !M! 回合内，无法再从牌中获得 格挡 值。"
    },
    "mysteryDungeon:BulbasaurRazorLeaf": {
        "NAME": "飞叶快刀",
        "DESCRIPTION": "失去 !M! 生命值。 NL 造成 !D! 点伤害。"
    },
    "mysteryDungeon:BulbasaurRest": {
        "NAME": "睡觉",
        "DESCRIPTION": "回复 !mysteryDungeon:M2! 点生命值。 mysterydungeon:睡觉 !M! 回合。"
    },
    "mysteryDungeon:BulbasaurSecretPower": {
        "NAME": "秘密之力",
        "DESCRIPTION": "固有。 NL 向手牌添加1张随机能力牌。 NL 消耗。",
        "UPGRADE_DESCRIPTION": "固有。 NL 向手牌添加1张随机升级后的能力牌。 NL 消耗。"
    },
    "mysteryDungeon:BulbasaurSeedBomb": {
        "NAME": "种子炸弹",
        "DESCRIPTION": "对随机敌人造成 !D! 点伤害X次。"
    },
    "mysteryDungeon:BulbasaurSleepPowder": {
        "NAME": "催眠粉",
        "DESCRIPTION": "向所有敌人施加 !M! 层 mysterydungeon:昏睡 。 NL 消耗。"
    },
    "mysteryDungeon:BulbasaurSludgeBomb": {
        "NAME": "污泥炸弹",
        "DESCRIPTION": "施加 !M! 层中毒。"
    },
    "mysteryDungeon:BulbasaurSolarBeam": {
        "NAME": "日光束",
        "DESCRIPTION": "对所有敌人造成 !D! 点伤害。 NL 下回合少抽 !M! 张牌。"
    },
    "mysteryDungeon:BulbasaurStrengthSap": {
        "NAME": "吸收力量",
        "DESCRIPTION": "敌人失去 !M! 点力量。 NL 若敌人失去力量，获得 !M! 点力量。 NL 消耗。"
    },
    "mysteryDungeon:BulbasaurStunSpore": {
        "NAME": "麻痹粉",
        "DESCRIPTION": "施加 !M! 层缓慢。 NL 消耗。",
        "UPGRADE_DESCRIPTION": "固有。 NL 施加 !M! 层缓慢。 NL 消耗。"
    },
    "mysteryDungeon:BulbasaurSunnyDay": {
        "NAME": "大晴天",
        "DESCRIPTION": "虚无。 NL 每回合开始时， NL 额外再抽一张牌，降低手牌中费用最高的牌1点耗能。",
        "UPGRADE_DESCRIPTION": "每回合开始时， NL 额外再抽一张牌，降低手牌中费用最高的牌1点耗能。"
    },
    "mysteryDungeon:BulbasaurSweetScent": {
        "NAME": "甜甜香气",
        "DESCRIPTION": "施加 !M! 层 mysterydungeon:防御下降 。 NL 施加 !M! 层易伤。"
    },
    "mysteryDungeon:BulbasaurSynthesis": {
        "NAME": "光合作用",
        "DESCRIPTION": "回复 !M! 点生命。 NL 下回合开始时， NL 额外再抽两张牌获得 [E] [E] 。 NL 消耗。"
    },
    "mysteryDungeon:BulbasaurTackle": {
        "NAME": "撞击",
        "DESCRIPTION": "造成 !D! 点伤害。"
    },
    "mysteryDungeon:BulbasaurToxic": {
        "NAME": "剧毒",
        "DESCRIPTION": "向所有敌人施加 !M! 层 mysterydungeon:剧毒 。 NL 消耗。",
        "UPGRADE_DESCRIPTION": "固有。 NL 向所有敌人施加 !M! 层 mysterydungeon:剧毒 。 NL 消耗。"
    },
    "mysteryDungeon:BulbasaurVenoshock": {
        "NAME": "毒液冲击",
        "DESCRIPTION": "造成 !D! 点伤害。 NL 根据敌人中毒层数，额外造成 !M! 点伤害。"
    },
    "mysteryDungeon:BulbasaurVineWhip": {
        "NAME": "藤鞭",
        "DESCRIPTION": "造成 !D! 点伤害。 NL 在下回合开始时，获得 [E] 。"
    },
    "mysteryDungeon:BulbasaurWorrySeed": {
        "NAME": "烦恼种子",
        "DESCRIPTION": "战斗结束后，卡牌奖励将额外包括1张牌。"
    },
    "mysteryDungeon:BulbasaurYawn": {
        "NAME": "哈欠",
        "DESCRIPTION": "虚无。 NL 在敌人行动之前施加 !M! 层 mysterydungeon:昏睡 。(在中毒之后). NL 消耗。",
        "UPGRADE_DESCRIPTION": "在敌人行动之前施加 !M! 层 mysterydungeon:昏睡 。(在中毒之后). NL 消耗。"
    },
    "mysteryDungeon:CharmanderAirCutter": {
        "NAME": "Air Cutter",
        "DESCRIPTION": "Deal !D! damage to ALL enemies !M! times."
    },
    "mysteryDungeon:CharmanderAirSlash": {
        "NAME": "Air Slash",
        "DESCRIPTION": "Deal !D! damage. NL If the enemy intends to attack, gain !B! Block."
    },
    "mysteryDungeon:CharmanderBlastBurn": {
        "NAME": "爆炸烈焰",
        "DESCRIPTION": "造成 !D! 点伤害。 NL 消耗你的手牌。"
    },
    "mysteryDungeon:CharmanderBlaze": {
        "NAME": "火焰",
        "DESCRIPTION": "获得2层易伤。 NL 每回合第一次能量为0后，获得 [E]。",
        "UPGRADE_DESCRIPTION": "获得2层易伤。 NL 每回合前两次能量为0后，获得 [E]。"
    },
    "mysteryDungeon:CharmanderCounter": {
        "NAME": "双倍奉还",
        "DESCRIPTION": "获得 !B! 点 格挡 。 NL 若受到攻击后失去全部防御，反击 !M! 点伤害。"
    },
    "mysteryDungeon:CharmanderDefend": {
        "NAME": "防御",
        "DESCRIPTION": "获得 !B! 点 格挡 。"
    },
    "mysteryDungeon:CharmanderDragonBreath": {
        "NAME": "龙息",
        "DESCRIPTION": "消耗牌堆每 !M! 张牌，获得 [E] 。",
        "UPGRADE_DESCRIPTION": "消耗牌堆每 !M! 张牌，获得 [E] 。 NL 获得 [E]."
    },
    "mysteryDungeon:CharmanderDragonClaw": {
        "NAME": "龙爪",
        "DESCRIPTION": "对所有敌人造成 !D! 点伤害。 NL (当使用金属 mysterydungeon:爪 时，鳞片)"
    },
    "mysteryDungeon:CharmanderDragonDance": {
        "NAME": "龙之舞",
        "DESCRIPTION": "消耗 !M! 张牌。 NL 抽 !mysteryDungeon:M2! 张牌。 NL (如果无法消耗 !M! 张牌，则该牌无法打出。)",
        "UPGRADE_DESCRIPTION": "抽 !mysteryDungeon:M2! 张牌。 NL 消耗 !M! 张牌。"
    },
    "mysteryDungeon:CharmanderDragonPulse": {
        "NAME": "龙之波动",
        "DESCRIPTION": "无法打出。 NL 抽到该牌时: NL 从消耗牌堆随机向抽牌堆顶部添加一张牌。 NL 触发 !M! 次后: 消耗。",
        "EXTENDED_DESCRIPTION": [
            "我无法打出这张牌。",
            "抽到时: 消耗。"
        ]
    },
    "mysteryDungeon:CharmanderDragonRage": {
        "NAME": "龙之怒",
        "DESCRIPTION": "虚无。 NL 敌人失去 !M! 点生命值。 消耗。"
    },
    "mysteryDungeon:CharmanderDragonRush": {
        "NAME": "龙之俯冲",
        "DESCRIPTION": "造成 !D! 点伤害。 NL 从你的消耗牌堆中选择一张牌并将其添加到你的弃牌堆。 NL 从你的牌堆随机抽一张牌。 消耗。"
    },
    "mysteryDungeon:CharmanderDragonTail": {
        "NAME": "龙尾",
        "DESCRIPTION": "无法打出。 NL 消耗时： NL 对所有敌人造成 !D! 点伤害。 NL 在你的抽牌堆顶部添加一张这张牌的复制品。",
        "UPGRADE_DESCRIPTION": "无法打出。 NL 消耗时： NL 对所有敌人造成 !D! 点伤害。 NL 在你的抽牌堆顶部添加一张这张牌的复制品。 NL 下回合，额外抽取1张牌。",
        "EXTENDED_DESCRIPTION": [
            "我无法打出这张牌。"
        ]
    },
    "mysteryDungeon:CharmanderDrought": {
        "NAME": "干旱",
        "DESCRIPTION": "当你施加 mysterydungeon:灼烧 时，额外施加 !M! 层。"
    },
    "mysteryDungeon:CharmanderEmber": {
        "NAME": "火花",
        "DESCRIPTION": "造成 !D! 点伤害。 NL 施加等同未被 格挡 伤害的 mysterydungeon:灼烧 。"
    },
    "mysteryDungeon:CharmanderExplorerForm": {
        "NAME": "小火龙·冒险者笔记",
        "DESCRIPTION": "虚无。 NL 回合开始时， 从消耗牌堆添加 !M! 张随机牌至手牌。 NL 每回合少抽取一张牌。",
        "UPGRADE_DESCRIPTION": "回合开始时， 从消耗牌堆添加 !M! 张随机牌至手牌。 NL 每回合少抽取一张牌。"
    },
    "mysteryDungeon:CharmanderFacade": {
        "NAME": "硬撑",
        "DESCRIPTION": "获得 !M! 层敏捷和 !mysteryDungeon:M2! 层人工制品。"
    },
    "mysteryDungeon:CharmanderFireBlast": {
        "NAME": "大字爆炎",
        "DESCRIPTION": "造成 !D! 点伤害。 NL 施加 !M! 层 mysterydungeon:灼烧 。 NL 消耗。"
    },
    "mysteryDungeon:CharmanderFireFang": {
        "NAME": "火焰牙",
        "DESCRIPTION": "造成 !D! 点伤害。 NL 施加 !M! 层 mysterydungeon:灼烧 。"
    },
    "mysteryDungeon:CharmanderFireSpin": {
        "NAME": "火焰漩涡",
        "DESCRIPTION": "虚无。 NL 施加等同 mysterydungeon:灼烧 层数的中毒。 NL 移除全部 mysterydungeon:灼烧 。",
        "UPGRADE_DESCRIPTION": "施加等同 mysterydungeon:灼烧 层数的中毒。 NL 移除全部 mysterydungeon:灼烧 。"
    },
    "mysteryDungeon:CharmanderFlamethrower": {
        "NAME": "喷射火焰",
        "DESCRIPTION": "对所有敌人造成 !D! 点伤害。 NL 对全体敌人施加 !M! 层 mysterydungeon:灼烧 。"
    },
    "mysteryDungeon:CharmanderFlareBlitz": {
        "NAME": "闪焰冲锋",
        "DESCRIPTION": "造成等同本场战斗消耗牌数量 !M! 倍的伤害。"
    },
    "mysteryDungeon:CharmanderTwister": {
        "NAME": "Twister",
        "DESCRIPTION": "Exhaust up to 4 cards. Deal !D! damage and apply !M! mysterydungeon:Burn per card exhausted that way. NL Exhaust.",
        "UPGRADE_DESCRIPTION": "Deal !D! damage and apply !M! mysterydungeon:Burn NL Exhaust up to 4 cards. NL Deal !D! damage and apply !M! mysterydungeon:Burn per card exhausted that way. NL Exhaust."
    },
    "mysteryDungeon:CharmanderFrustration": {
        "NAME": "迁怒",
        "DESCRIPTION": "每回合结束时，保留1张牌。这张牌被保留后变为虚无。"
    },
    "mysteryDungeon:CharmanderHeatCrash": {
        "NAME": "高温重压",
        "DESCRIPTION": "施加 !M! 层 mysterydungeon:灼烧 。 NL 当该敌人死亡时，对全部敌人造成等同于该敌人 mysterydungeon:灼烧 层数的伤害。 消耗。",
        "UPGRADE_DESCRIPTION": "施加 !M! 层 mysterydungeon:灼烧 。 NL 当该敌人死亡时，对全部敌人造成等同于该敌人 mysterydungeon:灼烧 层数的伤害。"
    },
    "mysteryDungeon:CharmanderHeatWave": {
        "NAME": "热风",
        "DESCRIPTION": "获得 !B! 点 格挡 。 NL 施加 !M! 层 mysterydungeon:灼烧 。 NL 消耗手牌中随机一张牌。",
        "UPGRADE_DESCRIPTION": "获得 !B! 点 格挡 。 NL 施加 !M! 层 mysterydungeon:灼烧 。 NL 选择手牌中一张牌消耗。"
    },
    "mysteryDungeon:CharmanderInferno": {
        "NAME": "炼狱",
        "DESCRIPTION": "对全体敌人施加 !M! 层 mysterydungeon:灼烧 。"
    },
    "mysteryDungeon:CharmanderMetalClaw": {
        "NAME": "金属爪",
        "DESCRIPTION": "造成 !D! 点伤害。 NL 本回合，所有“ mysterydungeon:爪 ”牌额外造成 !M! 点伤害。"
    },
    "mysteryDungeon:CharmanderOutrage": {
        "NAME": "逆鳞",
        "DESCRIPTION": "每消耗一张牌，对随机敌人施加 !M! 层 mysterydungeon:灼烧 。"
    },
    "mysteryDungeon:CharmanderOverheat": {
        "NAME": "过热",
        "DESCRIPTION": "造成 !D! 点伤害。 NL 对敌人造成等同于 mysterydungeon:灼烧 层数的额外伤害。"
    },
    "mysteryDungeon:CharmanderScaryFace": {
        "NAME": "鬼面",
        "DESCRIPTION": "获得 !B! 点 格挡 。 NL 施加 !M! 层 虚弱 。"
    },
    "mysteryDungeon:CharmanderScratch": {
        "NAME": "抓",
        "DESCRIPTION": "造成 !D! 点伤害。"
    },
    "mysteryDungeon:CharmanderShadowClaw": {
        "NAME": "影爪",
        "DESCRIPTION": "造成 !D! 点伤害。 NL 获得 !B! 点 格挡 。 NL 当使用金属 mysterydungeon:爪 时，该牌获得更多 格挡 。"
    },
    "mysteryDungeon:CharmanderRoost": {
        "NAME": "Roost",
        "DESCRIPTION": "The first time you exhaust a card each turn, add a random card to your hand.",
        "UPGRADE_DESCRIPTION": "The first 2 times you exhaust a card each turn, add a random card to your hand."
    },
    "mysteryDungeon:CharmanderSmokescreen": {
        "NAME": "烟幕",
        "DESCRIPTION": "获得 !M! 层无实体。 NL 获得 3 层 虚弱 。 NL 消耗。",
        "UPGRADE_DESCRIPTION": "获得 !M! 层无实体。 NL 获得 2 层 虚弱 。 NL 消耗。"
    },
    "mysteryDungeon:CharmanderSolarPower": {
        "NAME": "太阳能",
        "DESCRIPTION": "每回合开始时，若敌人被 mysterydungeon:灼烧 ，获得1点力量。",
        "UPGRADE_DESCRIPTION": "固有。 NL 每回合开始时，若敌人被 mysterydungeon:灼烧 ，获得1点力量。"
    },
    "mysteryDungeon:CharmanderTailWind": {
        "NAME": "Tail Wind",
        "DESCRIPTION": "At the start of your turn, draw !M! more card. NL The first card you play each turn costs 0 and exhausts."
    },
    "mysteryDungeon:CharmanderWillOWisp": {
        "NAME": "鬼火",
        "DESCRIPTION": "施加X层 虚弱 。 NL 施加3X层 mysterydungeon:灼烧 。 NL 消耗。",
        "UPGRADE_DESCRIPTION": "施加X+1层 虚弱 。 NL 施加3（X+1)层 mysterydungeon:灼烧 。 NL 消耗。"
    },
    "mysteryDungeon:ChikoritaAncientPower": {
        "NAME": "Ancient Power",
        "DESCRIPTION": "Deal !D! damage. NL If you are missing more then 30% of your health, deal !D! damage."
    },
    "mysteryDungeon:ChikoritaAromatherapy": {
        "NAME": "Aromatherapy",
        "DESCRIPTION": "Whenever you take damage, gain !M! Strength.",
        "UPGRADE_DESCRIPTION": "Whenever you take damage, gain !M! Strength. NL Next Turn Lose 1 HP"
    },
    "mysteryDungeon:ChikoritaBodySlam": {
        "NAME": "Body Slam",
        "DESCRIPTION": "Deal !D! damage. NL Next Turn Lose !M! HP."
    },
    "mysteryDungeon:ChikoritaConfide": {
        "NAME": "Confide",
        "DESCRIPTION": "Apply !M! Weak to ALL enemies. NL Apply !M! Evasiveness Drop to ALL enemies. NL Exhaust."
    },
    "mysteryDungeon:ChikoritaCut": {
        "NAME": "Cut",
        "DESCRIPTION": "Lose !M! HP. NL Deal !D! damage."
    },
    "mysteryDungeon:ChikoritaDefend": {
        "NAME": "Defend",
        "DESCRIPTION": "Gain !B! Block."
    },
    "mysteryDungeon:ChikoritaEnergyBall": {
        "NAME": "Energy Ball",
        "DESCRIPTION": "Deal !D! damage. NL Apply !M! Vulnerable."
    },
    "mysteryDungeon:ChikoritaExplorerForm": {
        "NAME": "Explorer Form",
        "DESCRIPTION": "Ethereal. NL When you heal HP, deal damage to ALL enemies equal to twice the amount healed.",
        "UPGRADE_DESCRIPTION": "When you heal HP, deal damage to ALL enemies equal to twice the amount healed."
    },
    "mysteryDungeon:ChikoritaFlail": {
        "NAME": "Flail",
        "DESCRIPTION": "Unplayable. NL Ethereal. NL When drawn, gain !M! Temporary Strength.",
        "UPGRADE_DESCRIPTION": "Unplayable. NL When drawn, gain !M! Temporary Strength.",
        "EXTENDED_DESCRIPTION": [
            "I can't play this card."
        ]
    },
    "mysteryDungeon:ChikoritaFuryCutter": {
        "NAME": "Fury Cutter",
        "DESCRIPTION": "Ethereal. NL Deal !D! damage. NL Increase this card damage by !M! this combat. NL Lose 2 HP. NL Bring back a copy of that card in your hand next turn and lose 2 HP. NL Exhaust."
    },
    "mysteryDungeon:ChikoritaGrassKnot": {
        "NAME": "Grass Knot",
        "DESCRIPTION": "Remove 33% of the enemy's remaining HP. NL Exhaust."
    },
    "mysteryDungeon:ChikoritaGrassPledge": {
        "NAME": "Grass Pledge",
        "DESCRIPTION": "Gain !M! Temporary HP. NL If you play another mysterydungeon:Pledge_Card this turn, activate a special effect."
    },
    "mysteryDungeon:ChikoritaGrassWhistle": {
        "NAME": "Grass Whistle",
        "DESCRIPTION": "Apply mysterydungeon:Asleep to ALL enemies. NL Exhaust.",
        "UPGRADE_DESCRIPTION": "Retain. NL Apply mysterydungeon:Asleep to ALL enemies. NL Exhaust."
    },
    "mysteryDungeon:ChikoritaGrassyTerrain": {
        "NAME": "Grassy Terrain",
        "DESCRIPTION": "Increase your max HP by !M!."
    },
    "mysteryDungeon:ChikoritaGrowl": {
        "NAME": "Growl",
        "DESCRIPTION": "Apply !M! Weak to ALL enemies."
    },
    "mysteryDungeon:ChikoritaHealPulse": {
        "NAME": "Heal Pulse",
        "DESCRIPTION": "Whenever you inflict self damage or gain HP during your turn, gain !M! block.",
        "UPGRADE_DESCRIPTION": "Innate. NL Whenever you inflict self damage or gain HP during your turn, gain !M! block."
    },
    "mysteryDungeon:ChikoritaLeafGuard": {
        "NAME": "Leaf Guard",
        "DESCRIPTION": "At the end of your turn, remove all debuff you possess. For each debuff removed this way lose !M! HP."
    },
    "mysteryDungeon:ChikoritaLeafStorm": {
        "NAME": "Leaf Storm",
        "DESCRIPTION": "Lose 1 HP !M! times. NL Deal !D! damage !M! times."
    },
    "mysteryDungeon:ChikoritaMagicCoat": {
        "NAME": "Magic Coat",
        "DESCRIPTION": "Gain !M! Temporary HP. NL Draw 1 card."
    },
    "mysteryDungeon:ChikoritaMagicalLeaf": {
        "NAME": "Magical Leaf",
        "DESCRIPTION": "Deal !D! damage !M! times to random enemies."
    },
    "mysteryDungeon:ChikoritaNaturalGift": {
        "NAME": "Natural Gift",
        "DESCRIPTION": "Gain !M! Strength. NL Gain !mysteryDungeon:M2! Block at the end of your turn."
    },
    "mysteryDungeon:ChikoritaNaturePowerGrassland": {
        "NAME": "Nature Power: Grassland",
        "DESCRIPTION": "Lose 3 HP. NL Draw !M! cards."
    },
    "mysteryDungeon:ChikoritaOvergrow": {
        "NAME": "Overgrow",
        "DESCRIPTION": "Each time your recover counter reaches 0, gain !M! Strength.",
        "UPGRADE_DESCRIPTION": "Innate. NL Each time your recover counter reaches 0, gain !M! Strength."
    },
    "mysteryDungeon:ChikoritaPetalBlizzard": {
        "NAME": "Petal Blizzard",
        "DESCRIPTION": "Deal !D! damage to ALL enemies."
    },
    "mysteryDungeon:ChikoritaPetalDance": {
        "NAME": "Petal Dance",
        "DESCRIPTION": "Unplayable. NL When drawn: Gain !M! Temporary HP and deal !D! damage to all enemies. NL Increase the amount of Temporary HP by 1 and the damage by 4 this combat.",
        "EXTENDED_DESCRIPTION": [
            "I can't play this card."
        ]
    },
    "mysteryDungeon:ChikoritaRazorLeaf": {
        "NAME": "Razor Leaf",
        "DESCRIPTION": "Lose !M! HP. NL Deal !D! damage."
    },
    "mysteryDungeon:ChikoritaRefresh": {
        "NAME": "Refresh",
        "DESCRIPTION": "Gain !M! Temporary HP."
    },
    "mysteryDungeon:ChikoritaSecretPower": {
        "NAME": "Secret Power",
        "DESCRIPTION": "Innate. NL Add a random Power to your hand. NL Exhaust.",
        "UPGRADE_DESCRIPTION": "Innate. NL Add a random upgraded Power to your hand. NL Exhaust."
    },
    "mysteryDungeon:ChikoritaSeedBomb": {
        "NAME": "Seed Bomb",
        "DESCRIPTION": "Deal !D! damage. NL Next turn draw 2 more cards."
    },
    "mysteryDungeon:ChikoritaSnore": {
        "NAME": "Snore",
        "DESCRIPTION": "If the enemy intends to attack, apply 1 mysterydungeon:Asleep. NL Exhaust.",
        "UPGRADE_DESCRIPTION": "If the enemy intends to attack, apply 1 mysterydungeon:Asleep."
    },
    "mysteryDungeon:ChikoritaSolarBeam": {
        "NAME": "Solar Beam",
        "DESCRIPTION": "Deal !D! damage to ALL enemies. NL Draw !M! less cards during your next turn."
    },
    "mysteryDungeon:ChikoritaSunnyDay": {
        "NAME": "Sunny Day",
        "DESCRIPTION": "Ethereal. NL When dealing damage to yourself, for every 3 HP lost draw a card.",
        "UPGRADE_DESCRIPTION": "When dealing damage to yourself, for every 3 HP lost draw a card."
    },
    "mysteryDungeon:ChikoritaSweetScent": {
        "NAME": "Sweet Scent",
        "DESCRIPTION": "Apply !M! mysterydungeon:Evasiveness_Drop. NL Apply !M! Vulnerable"
    },
    "mysteryDungeon:ChikoritaSynthesis": {
        "NAME": "Synthesis",
        "DESCRIPTION": "Unplayable. NL When drawn: Heal !M! HP. NL After activating this effect !mysteryDungeon:M2! times: Exhaust.",
        "EXTENDED_DESCRIPTION": [
            "I can't play this card.",
            "When Drawn: Exhaust."
        ]
    },
    "mysteryDungeon:ChikoritaTackle": {
        "NAME": "Tackle",
        "DESCRIPTION": "Deal !D! damage."
    },
    "mysteryDungeon:ChikoritaVineWhip": {
        "NAME": "Vine Whip",
        "DESCRIPTION": "Deal !D! damage. NL Put a card from your discard pile into your draw pile.",
        "UPGRADE_DESCRIPTION": "Deal !D! damage. NL Draw !M! cards."
    },
    "mysteryDungeon:ChikoritaWorrySeed": {
        "NAME": "Worry Seed",
        "DESCRIPTION": "Unplayable. NL Ethereal. NL When drawn draw !M! cards. NL While in hand, Lose 1 HP per card played.",
        "UPGRADE_DESCRIPTION": "Unplayable. NL When drawn draw !M! cards. NL While in hand, Lose 1 HP per card played.",
        "EXTENDED_DESCRIPTION": [
            "I can't play this card."
        ]
    },
    "mysteryDungeon:ChikoritaWringOut": {
        "NAME": "Wring Out",
        "DESCRIPTION": "Deal !D! damage. NL Lose !M! HP."
    },
    "mysteryDungeon:CyndaquilBlastBurn": {
        "NAME": "Blast Burn",
        "DESCRIPTION": "Deal !D! damage. NL Cause an Eruption. NL End your Turn."
    },
    "mysteryDungeon:CyndaquilBurnUp": {
        "NAME": "Fire Pledge",
        "DESCRIPTION": "Add 2 Burn status cards to your draw pile. NL Apply !M! mysterydungeon:Burn to an enemy."
    },
    "mysteryDungeon:CyndaquilCounter": {
        "NAME": "Counter",
        "DESCRIPTION": "At the end of your turn, spend all leftover energy. For every energy spent this way gain !M! block.",
        "UPGRADE_DESCRIPTION": "At the end of your turn, spend all leftover energy. For every energy spent this way gain !M! Block. NL Gain !B! Block."
    },
    "mysteryDungeon:CyndaquilCrushClaw": {
        "NAME": "Crush Claw",
        "DESCRIPTION": "Deal !D! damage to ALL enemies. NL Your next mysterydungeon:Eruption will deal 50% more damage. NL Exhaust.",
        "UPGRADE_DESCRIPTION": "Deal !D! damage to ALL enemies. NL Your next mysterydungeon:Eruption will deal 50% more damage."
    },
    "mysteryDungeon:CyndaquilCurse": {
        "NAME": "Curse",
        "DESCRIPTION": "Each turn, the first time you draw a Curse or a Status, gain [E].",
        "UPGRADE_DESCRIPTION": "Each turn, the first 2 times you draw a Curse or a Status, gain [E]."
    },
    "mysteryDungeon:CyndaquilDefend": {
        "NAME": "Defend",
        "DESCRIPTION": "Gain !B! block."
    },
    "mysteryDungeon:CyndaquilEmber": {
        "NAME": "Ember",
        "DESCRIPTION": "Deal !D! damage. NL Apply !M! mysterydungeon:Burn."
    },
    "mysteryDungeon:CyndaquilEruption": {
        "NAME": "Eruption",
        "DESCRIPTION": "Trigger an mysterydungeon:Eruption that hits ALL enemies. NL End your turn. NL Exhaust.",
        "UPGRADE_DESCRIPTION": "Trigger an mysterydungeon:Eruption that hits ALL enemies. NL End your turn."
    },
    "mysteryDungeon:CyndaquilExplorerForm": {
        "NAME": "Explorer Form",
        "DESCRIPTION": "Whenever you apply mysterydungeon:Burn to an enemy, deal !M! damage to that enemy."
    },
    "mysteryDungeon:CyndaquilFacade": {
        "NAME": "Facade",
        "DESCRIPTION": "Gain !M! Dexterity. NL Add a *Burn to your draw pile."
    },
    "mysteryDungeon:CyndaquilFireBlast": {
        "NAME": "Fire Blast",
        "DESCRIPTION": "Apply !M! mysterydungeon:Burn. NL Increase the amount of mysterydungeon:Burn this card applies by !mysteryDungeon:M2! permanently. NL Exhaust."
    },
    "mysteryDungeon:CyndaquilFirePledge": {
        "NAME": "Fire Pledge",
        "DESCRIPTION": "Apply !M! mysterydungeon:Burn to all enemies. NL If you play another mysterydungeon:Pledge card this turn, activate a special effect."
    },
    "mysteryDungeon:CyndaquilFlameBurst": {
        "NAME": "Flame Burst",
        "DESCRIPTION": "Apply !M! mysterydungeon:Burn. NL Next turn, trigger an mysterydungeon:Eruption.",
        "UPGRADE_DESCRIPTION": "Apply !M! mysterydungeon:Burn. NL Next turn, cause an mysterydungeon:Eruption. NL Your next Eruption Deals 50% more damage."
    },
    "mysteryDungeon:CyndaquilFlameCharge": {
        "NAME": "Flame Charge",
        "DESCRIPTION": "Deal !D! damage. NL Gain !B! Block. NL Apply !M! mysterydungeon:Burn."
    },
    "mysteryDungeon:CyndaquilFlamethrower": {
        "NAME": "Flamethrower",
        "DESCRIPTION": "Add a Burn status card in your draw pile. NL Deal !D! damage to a random enemy !M! times. NL Apply 9 mysterydungeon:Burn to random enemies !M! times."
    },
    "mysteryDungeon:CyndaquilFlameWheel": {
        "NAME": "Flame Wheel",
        "DESCRIPTION": "Apply !M! mysterydungeon:Burn twice. NL Cause an mysterydungeon:Eruption. NL End your turn.",
        "UPGRADE_DESCRIPTION": "Retain. NL Apply !M! mysterydungeon:Burn twice. NL Cause an mysterydungeon:Eruption. NL End your turn."
    },
    "mysteryDungeon:CyndaquilFlareBlitz": {
        "NAME": "Flare Blitz",
        "DESCRIPTION": "Add 1 Void in your draw pile. NL Deal !D! damage. NL If the attack is Fatal, Gain [E] [E]."
    },
    "mysteryDungeon:CyndaquilFlashFire": {
        "NAME": "Flash Fire",
        "DESCRIPTION": "Add 2 Burn status card in your draw pile. NL Each time you play a card apply !M! mysterydungeon:Burn to all enemies.",
        "UPGRADE_DESCRIPTION": "Innate. NL Add 2 Burn status card in your draw pile. NL Each time you play a card apply !M! mysterydungeon:Burn to all enemies."
    },
    "mysteryDungeon:CyndaquilFling": {
        "NAME": "Fling",
        "DESCRIPTION": "Apply 5 mysterydungeon:Burn twice. NL Gain [E]. NL Exhaust.",
        "UPGRADE_DESCRIPTION": "Apply 5 mysterydungeon:Burn twice. NL Gain [E] [E]. NL Exhaust."
    },
    "mysteryDungeon:CyndaquilFrustration": {
        "NAME": "Frustration",
        "DESCRIPTION": "Apply 12 mysterydungeon:Burn. NL Next turn, at the end of your turn cause an mysterydungeon:Eruption.",
        "UPGRADE_DESCRIPTION": "Retain. NL Apply 12 mysterydungeon:Burn. NL Next turn, at the end of your turn cause an mysterydungeon:Eruption."
    },
    "mysteryDungeon:CyndaquilSmokescreen": {
        "NAME": "Smokescreen",
        "DESCRIPTION": "Gain !B! Block. NL Next turn gain [E]."
    },
    "mysteryDungeon:CyndaquilHeatWave": {
        "NAME": "Heat Wave",
        "DESCRIPTION": "Gain !B! block. NL Whenever you are attacked this turn, apply 5 mysterydungeon:Burn to your attacker."
    },
    "mysteryDungeon:CyndaquilHowl": {
        "NAME": "Howl",
        "DESCRIPTION": "Add !M! *Burn to your draw pile. NL Next turn gain [E] [E] [E]."
    },
    "mysteryDungeon:CyndaquilIncinerate": {
        "NAME": "Incinerate",
        "DESCRIPTION": "Apply !M! mysterydungeon:Burn."
    },
    "mysteryDungeon:CyndaquilInferno": {
        "NAME": "Inferno",
        "DESCRIPTION": "Your next mysterydungeon:Eruption will not remove any burn stacks. NL Exhaust.",
        "UPGRADE_DESCRIPTION": "Your next eruption will not remove any burn stacks. NL Apply !M! mysterydungeon:Burn to all enemies. NL Exhaust."
    },
    "mysteryDungeon:CyndaquilLaserFocus": {
        "NAME": "Laser Focus",
        "DESCRIPTION": "Gain [E] [E].",
        "UPGRADE_DESCRIPTION": "Gain [E] [E]. NL Draw a card."
    },
    "mysteryDungeon:CyndaquilLavaPlume": {
        "NAME": "Lava Plume",
        "DESCRIPTION": "Whenever you trigger an mysterydungeon:Eruption, apply !M! mysterydungeon:Burn to the target."
    },
    "mysteryDungeon:CyndaquilLeer": {
        "NAME": "Flame Wheel",
        "DESCRIPTION": "Apply !M! Vulnerable.",
        "UPGRADE_DESCRIPTION": "Apply !M! Vulnerable. NL Remove all the enemies block"
    },
    "mysteryDungeon:CyndaquilNaturePowerMountain": {
        "NAME": "Nature Power: Mountain",
        "DESCRIPTION": "For the next X turns, mysterydungeon:Burn stacks do not decrease by themselves on the target.",
        "UPGRADE_DESCRIPTION": "For X+1 turns, mysterydungeon:Burn stacks do not decrease naturally on a chosen enemy."
    },
    "mysteryDungeon:CyndaquilOverheat": {
        "NAME": "Overheat",
        "DESCRIPTION": "Retain. NL Trigger an mysterydungeon:Eruption. NL Exhaust."
    },
    "mysteryDungeon:CyndaquilReversal": {
        "NAME": "Reversal",
        "DESCRIPTION": "If the enemy has mysterydungeon:Burn, gain !B! Block. NL If the enemy has no mysterydungeon:Burn stacks, apply !M! mysterydungeon:Burn."
    },
    "mysteryDungeon:CyndaquilRockTomb": {
        "NAME": "Rock Tomb",
        "DESCRIPTION": "Deal !D! damage and apply !M! Weak to ALL enemies."
    },
    "mysteryDungeon:CyndaquilRockSlide": {
        "NAME": "Rock Slide",
        "DESCRIPTION": "Deal !D! damage. If the enemy has mysterydungeon:Burn stacks, gain [E] [E] next turn."
    },
    "mysteryDungeon:CyndaquilRollout": {
        "NAME": "Rollout",
        "DESCRIPTION": "Deal !D! damage. NL Gain !B! Block per card played this turn."
    },
    "mysteryDungeon:CyndaquilShadowClaw": {
        "NAME": "Shadow Claw",
        "DESCRIPTION": "Add a *Dazed in your draw pile. NL Deal !D! damage."
    },
    "mysteryDungeon:CyndaquilSleepTalk": {
        "NAME": "Sleep Talk",
        "DESCRIPTION": "When you create a Status card, draw !M! card.",
        "UPGRADE_DESCRIPTION": "For each created Status card, draw !M! card. NL Draw a card."
    },
    "mysteryDungeon:CyndaquilTackle": {
        "NAME": "Tackle",
        "DESCRIPTION": "Deal !D! damage."
    },
    "mysteryDungeon:CyndaquilWillOWisp": {
        "NAME": "Will-O-Wisp",
        "DESCRIPTION": "Apply !M! mysterydungeon:Burn X times.",
        "UPGRADE_DESCRIPTION": "Retain. NL Apply !M! mysterydungeon:Burn X+1 times."
    },
    "mysteryDungeon:MeowthAmnesia": {
        "NAME": "Amnesia",
        "DESCRIPTION": "Spend 12 gold. NL Prevent the next !M! time you would lose HP."
    },
    "mysteryDungeon:MeowthAssurance": {
        "NAME": "Assurance",
        "DESCRIPTION": "Innate. NL Deal !D! damage. NL If the enemy's attacking, apply !M! Weak and gain 7 gold. NL Exhaust."
    },
    "mysteryDungeon:MeowthAttract": {
        "NAME": "Attract",
        "DESCRIPTION": "Gain !B! block. NL Spend !M! gold. NL Create a *Snatch in your hand. NL Exhaust.",
        "UPGRADE_DESCRIPTION": "Gain !B! block. NL Spend !M! gold. NL Create an upgraded Snatch in your hand. NL Exhaust."
    },
    "mysteryDungeon:MeowthCaptivate": {
        "NAME": "Captivate",
        "DESCRIPTION": "Spend !M! gold. NL This turn, the target loses !mysteryDungeon:M2! Strength."
    },
    "mysteryDungeon:MeowthCovet": {
        "NAME": "Covet",
        "DESCRIPTION": "Apply !M! Strength to a random enemy. NL Gain !mysteryDungeon:M2! gold."
    },
    "mysteryDungeon:MeowthDarkPulse": {
        "NAME": "Dark Pulse",
        "DESCRIPTION": "Spend 10 gold. NL Deal !D! damage to ALL enemies. NL Add a card from your discard pile into your hand. NL Exhaust.",
        "UPGRADE_DESCRIPTION": "Spend 10 gold. NL Deal !D! damage to ALL enemies. NL Add a card from your discard pile into your hand."
    },
    "mysteryDungeon:MeowthDefend": {
        "NAME": "Defend",
        "DESCRIPTION": "Gain !B! Block."
    },
    "mysteryDungeon:MeowthExplorerForm": {
        "NAME": "Explorer Form",
        "DESCRIPTION": "Every turn the first gold cost is free.",
        "UPGRADE_DESCRIPTION": "Innate. NL Every turn the first gold cost is free."
    },
    "mysteryDungeon:MeowthFakeTears": {
        "NAME": "Fake Tears",
        "DESCRIPTION": "Spend !M! gold. NL Gain !B! Block."
    },
    "mysteryDungeon:MeowthFeint": {
        "NAME": "Feint",
        "DESCRIPTION": "Remove all block from the enemy. NL Deal damage equal to the amount of block removed.",
        "UPGRADE_DESCRIPTION": "Remove all Block from the enemy. NL Deal damage equal to 4 more than the amount of Block removed.",
        "EXTENDED_DESCRIPTION": [
            " NL (Deals !D! damage.)"
        ]
    },
    "mysteryDungeon:MeowthFlash": {
        "NAME": "Flash",
        "DESCRIPTION": "Spend 10 gold. NL Gain !M! plated armor. NL Exhaust."
    },
    "mysteryDungeon:MeowthFlatter": {
        "NAME": "Flatter",
        "DESCRIPTION": "Apply !M! Strength to ALL enemies. NL Gain !B! Block."
    },
    "mysteryDungeon:MeowthFlurry": {
        "NAME": "Flurry",
        "DESCRIPTION": "Ethereal. NL Spend !M! gold. NL Deal !D! damage. NL Exhaust."
    },
    "mysteryDungeon:MeowthFoulPlay": {
        "NAME": "Foul Play",
        "DESCRIPTION": "Deal !D! damage. NL If the last card you played was an Attack, apply !M! Weak."
    },
    "mysteryDungeon:MeowthFurySwipes": {
        "NAME": "Fury Swipes",
        "DESCRIPTION": "Deal !D! damage. NL If you have !M! gold, spend it and increase permanently this card's damage by !mysteryDungeon:M2!. NL Exhaust."
    },
    "mysteryDungeon:MeowthHappyHour": {
        "NAME": "Happy Hour",
        "DESCRIPTION": "Gain !M! gold. NL Increase the amount by !mysteryDungeon:M2! permanently. NL Exhaust."
    },
    "mysteryDungeon:MeowthHoneClaws": {
        "NAME": "Hone Claws",
        "DESCRIPTION": "Give an enemy !B! block. NL Gain !M! Strength"
    },
    "mysteryDungeon:MeowthHyperVoice": {
        "NAME": "Hyper Voice",
        "DESCRIPTION": "Ethereal. NL Spend !M! gold. NL Deal !D! damage. NL Increase gold cost by 4 and damage by 6 for the combat. NL Return the card to your hand.",
        "UPGRADE_DESCRIPTION": "Spend !M! gold. NL Deal !D! damage. NL Increase gold cost by 4 and damage by 6 for the combat. NL Return the card to your hand."
    },
    "mysteryDungeon:MeowthLastResort": {
        "NAME": "Last Resort",
        "DESCRIPTION": "Spend !M! gold. Discard your hand. NL Draw 10 cards. NL Exhaust.",
        "UPGRADE_DESCRIPTION": "Retain. NL Spend !M! gold. Discard your hand. NL Draw 10 cards. NL Exhaust."
    },
    "mysteryDungeon:MeowthLashOut": {
        "NAME": "Lash Out",
        "DESCRIPTION": "Whenever you apply Strength or Block to an enemy create !M! *Flurry in your hand.",
        "UPGRADE_DESCRIPTION": "Whenever you apply Strength or Block to an enemy create !M! upgraded *Flurry in your hand."
    },
    "mysteryDungeon:MeowthNastyPlot": {
        "NAME": "Nasty Plot",
        "DESCRIPTION": "Spend !M! gold. NL Draw !mysteryDungeon:M2! cards."
    },
    "mysteryDungeon:MeowthNightSlash": {
        "NAME": "Night Slash",
        "DESCRIPTION": "Spend 10 gold. NL Deal !D! damage to ALL enemies. NL Add ALL 0 cost cards in your discard pile into your hand. NL Exhaust."
    },
    "mysteryDungeon:MeowthPayday": {
        "NAME": "Pay Day",
        "DESCRIPTION": "Deal !D! damage. NL Deal additionnal damage equal to money spent this combat.",
        "UPGRADE_DESCRIPTION": "Retain. NL Deal !D! damage. NL Deal additionnal damage equal to money spent this combat."
    },
    "mysteryDungeon:MeowthPowerGem": {
        "NAME": "Power Gem",
        "DESCRIPTION": "Deal !D! damage. NL The next card with a gold cost this turn is free.",
        "UPGRADE_DESCRIPTION": "Deal !D! damage. NL The next !M! cards with a gold cost this turn are free."
    },
    "mysteryDungeon:MeowthPsychUp": {
        "NAME": "Psych Up",
        "DESCRIPTION": "When you apply Strength to an enemy, gain !M! Strength.",
        "UPGRADE_DESCRIPTION": "When you apply Strength to an enemy, gain !M! Strength."
    },
    "mysteryDungeon:MeowthPunishment": {
        "NAME": "Punishment",
        "DESCRIPTION": "Deal !D! damage. NL Deal Addditionnal damage equal to !M! times the enemy's Strength."
    },
    "mysteryDungeon:MeowthRoar": {
        "NAME": "Roar",
        "DESCRIPTION": "Apply !M! Strength. NL Apply 99 Weak. NL Exhaust."
    },
    "mysteryDungeon:MeowthSnatch": {
        "NAME": "Snatch",
        "DESCRIPTION": "Deal !D! damage. NL Gain !M! gold. NL Create an Attract in your hand. NL Exhaust.",
        "UPGRADE_DESCRIPTION": "Deal !D! damage. NL Gain !M! gold. NL Create an Attract+ in your hand. NL Exhaust."
    },
    "mysteryDungeon:MeowthScratch": {
        "NAME": "Scratch",
        "DESCRIPTION": "Deal !D! damage."
    },
    "mysteryDungeon:MeowthScreech": {
        "NAME": "Screech",
        "DESCRIPTION": "Give an enemy !M! vulnerable and !B! block."
    },
    "mysteryDungeon:MeowthSnarl": {
        "NAME": "Snarl",
        "DESCRIPTION": "Apply 8 Block. NL Gain !B! Block."
    },
    "mysteryDungeon:MeowthSpite": {
        "NAME": "Spite",
        "DESCRIPTION": "Spend !M! X gold. NL Gain 2X Strength. NL Exhaust."
    },
    "mysteryDungeon:MeowthSwagger": {
        "NAME": "Swagger",
        "DESCRIPTION": "Apply !M! Strength. NL Apply Stun."
    },
    "mysteryDungeon:MeowthSwitcheroo": {
        "NAME": "Switcheroo",
        "DESCRIPTION": "Exchange your Strength with the target's Strength. NL Exhaust.",
        "UPGRADE_DESCRIPTION": "Lose !M! Strength. NL Exchange your Strength with the target's Strength. NL Exhaust."
    },
    "mysteryDungeon:MeowthTaunt": {
        "NAME": "Taunt",
        "DESCRIPTION": "Gain !M! gold. NL End your turn."
    },
    "mysteryDungeon:MeowthTechnician": {
        "NAME": "Technician",
        "DESCRIPTION": "Innate. NL At the start of your turn create a *Flurry in your hand.",
        "UPGRADE_DESCRIPTION": "Innate. NL At the start of your turn create an upgraded *Flurry in your hand."
    },
    "mysteryDungeon:MeowthThief": {
        "NAME": "Thief",
        "DESCRIPTION": "Deal !D! damage to !M! random enemies. NL Gain 5 gold !M! times. NL Exhaust."
    },
    "mysteryDungeon:MeowthThroatChop": {
        "NAME": "Throat Chop",
        "DESCRIPTION": "Deal !D! damage. NL Gain !B! block. NL Gain !M! gold."
    },
    "mysteryDungeon:MeowthUnnerve": {
        "NAME": "Unnerve",
        "DESCRIPTION": "Each time you spend a total of 25 gold this combat, gain !M! Plated Armor."
    },
    "mysteryDungeon:MeowthUTurn": {
        "NAME": "U-Turn",
        "DESCRIPTION": "Spend !M! gold. NL Create a card from your partner's deck in hand. NL It cost 0 this turn. NL Exhaust.",
        "UPGRADE_DESCRIPTION": "Spend !M! gold. NL Create a card from your partner's deck in hand. NL It cost 0 this combat. NL Exhaust."
    },
    "mysteryDungeon:PikachuAgility": {
        "NAME": "高速移动",
        "DESCRIPTION": "当进入姿态时， 抽 !M! 张牌。",
        "UPGRADE_DESCRIPTION": "固有。 NL 当进入姿态时， 抽 !M! 张牌。"
    },
    "mysteryDungeon:PikachuChargeBeam": {
        "NAME": "充电光束",
        "DESCRIPTION": " mysterydungeon:惰性 。 NL 生成 !M! 个闪电。 NL 消耗。"
    },
    "mysteryDungeon:PikachuCharge": {
        "NAME": "充电",
        "DESCRIPTION": "获得 !M! 点集中。 NL 移除全部充能球。"
    },
    "mysteryDungeon:PikachuCharm": {
        "NAME": "撒娇",
        "DESCRIPTION": "施加 !M! 层易伤。 NL 施加 !M! 层跟踪锁定。 NL 消耗。"
    },
    "mysteryDungeon:PikachuDefend": {
        "NAME": "防御",
        "DESCRIPTION": "获得 !B! 点 格挡 。"
    },
    "mysteryDungeon:PikachuDischarge": {
        "NAME": "放电",
        "DESCRIPTION": "造成 !D! 点伤害。 NL 激发 !M! 个充能球。",
        "UPGRADE_DESCRIPTION": "造成 !D! 点伤害。 NL 激发 !M! 个充能球。"
    },
    "mysteryDungeon:PikachuEerieImpulse": {
        "NAME": "怪异电波",
        "DESCRIPTION": "获得 !M! 点力量。 NL 获得 !M! 层敏捷。 NL 失去2点集中。"
    },
    "mysteryDungeon:PikachuElectricTerrain": {
        "NAME": "电气场地",
        "DESCRIPTION": " mysterydungeon:惰性 。 NL 进入 mysterydungeon:正极态 。 NL 消耗。",
        "UPGRADE_DESCRIPTION": " mysterydungeon:惰性 。 NL 保留。 NL 进入 mysterydungeon:正极态 。 NL 消耗。"
    },
    "mysteryDungeon:PikachuElectroBall": {
        "NAME": "电球",
        "DESCRIPTION": "激发下个充能球 !M! 次。 NL 每使用1次，在本场战斗中，次数增加1次。"
    },
    "mysteryDungeon:PikachuElectroweb": {
        "NAME": "电子网",
        "DESCRIPTION": " mysterydungeon:惰性 。 NL 向手牌放置弃牌堆中的 !M! 张牌。 NL 消耗。",
        "UPGRADE_DESCRIPTION": " mysterydungeon:惰性 。 NL 保留。 NL 向手牌放置弃牌堆中的 !M! 张牌。 NL 消耗。"
    },
    "mysteryDungeon:PikachuEncore": {
        "NAME": "再来一次",
        "DESCRIPTION": " mysterydungeon:惰性 。 NL 本回合，你的下张攻击牌或技能牌将打出两次。",
        "UPGRADE_DESCRIPTION": " mysterydungeon:惰性 。 NL 本回合，你的下 !M! 张攻击牌或技能牌将打出两次。"
    },
    "mysteryDungeon:PikachuExplorerForm": {
        "NAME": "皮卡丘·冒险者笔记",
        "DESCRIPTION": "回合开始时， 激发下个充能球，然后生成 !M! 个闪电充能球。",
        "UPGRADE_DESCRIPTION": "回合开始时， 激发下个充能球，然后生成 !M! 个闪电充能球。"
    },
    "mysteryDungeon:PikachuHiddenPower": {
        "NAME": "觉醒力量",
        "DESCRIPTION": " mysterydungeon:惰性 。 NL 向手牌加入一张随机的攻击牌或技能牌。 NL 这张牌本回合耗能为0。 NL 消耗。"
    },
    "mysteryDungeon:PikachuIronTail": {
        "NAME": "铁尾",
        "DESCRIPTION": "造成 !D! 点伤害。 NL 在本场战斗中，增加这张牌 !M! 点伤害。"
    },
    "mysteryDungeon:PikachuLightningRod": {
        "NAME": "避雷针",
        "DESCRIPTION": "获得 !B! 点 格挡 。 NL 生成 !M! 个闪电充能球。"
    },
    "mysteryDungeon:PikachuLightScreen": {
        "NAME": "光墙",
        "DESCRIPTION": "在你的回合结束时，每有一个空充能球栏位，获得 !M! 点 格挡 。"
    },
    "mysteryDungeon:PikachuNastyPlot": {
        "NAME": "诡计",
        "DESCRIPTION": "获得 !M! 个充能球栏位。",
        "UPGRADE_DESCRIPTION": "获得 !M! 个充能球栏位。"
    },
    "mysteryDungeon:PikachuNuzzle": {
        "NAME": "蹭蹭脸颊",
        "DESCRIPTION": "每个充能球造成 !D! 点伤害。",
        "UPGRADE_DESCRIPTION": "造成 !D! 点伤害。 NL 每个充能球造成 !D! 点伤害。"
    },
    "mysteryDungeon:PikachuPlayNice": {
        "NAME": "和睦相处",
        "DESCRIPTION": "获得 !B! 点 格挡 。 NL 抽 !M! 张牌。"
    },
    "mysteryDungeon:PikachuPlayRough": {
        "NAME": "嬉闹",
        "DESCRIPTION": "造成 !D! 点伤害。 NL 施加 !M! 层 虚弱 。"
    },
    "mysteryDungeon:PikachuQuickAttack": {
        "NAME": "电光一闪",
        "DESCRIPTION": "造成 !D! 点伤害。"
    },
    "mysteryDungeon:PikachuReflect": {
        "NAME": "反射壁",
        "DESCRIPTION": "获得 !B! 点 格挡 。 NL 在本场战斗中，增加这张牌 !M! 点 格挡 。"
    },
    "mysteryDungeon:PikachuSafeguard": {
        "NAME": "神秘守护",
        "DESCRIPTION": "获得 !B! 点 格挡 。 NL 本回合保留手牌。",
        "UPGRADE_DESCRIPTION": "获得 !B! 点 格挡 。 NL 保留手牌 !M! 次。"
    },
    "mysteryDungeon:PikachuShockWave": {
        "NAME": "电击波",
        "DESCRIPTION": "对所有敌人造成 !D! 点伤害。 NL 对所有敌人施加 !M! 层跟踪锁定。"
    },
    "mysteryDungeon:PikachuSpark": {
        "NAME": "电光",
        "DESCRIPTION": " mysterydungeon:惰性 。 NL 造成 !D! 点伤害。 NL 在你的回合结束后，指针不会复位。 NL 消耗。"
    },
    "mysteryDungeon:PikachuSpeedSwap": {
        "NAME": "速度互换",
        "DESCRIPTION": " mysterydungeon:惰性 。 NL 进入 mysterydungeon:负极态 。 NL 消耗。",
        "UPGRADE_DESCRIPTION": " mysterydungeon:惰性 。 NL 保留。 NL 进入 mysterydungeon:负极态 。 NL 消耗。"
    },
    "mysteryDungeon:PikachuStatic": {
        "NAME": "静电",
        "DESCRIPTION": "每受一次伤害，触发下个充能球的激发效果 !M! 次。",
        "UPGRADE_DESCRIPTION": "固有。 NL 每受一次伤害触发下个充能球的激发效果 !M! 次。"
    },
    "mysteryDungeon:PikachuSweetKiss": {
        "NAME": "天使之吻",
        "DESCRIPTION": "本回合，每当你进入或退出一次姿态，给予所有敌人 !M! 层 虚弱 。"
    },
    "mysteryDungeon:PikachuSwift": {
        "NAME": "高速星星",
        "DESCRIPTION": "对所有敌人造成 !D! 点伤害。 NL 抽 !M! 张牌。"
    },
    "mysteryDungeon:PikachuTackle": {
        "NAME": "撞击",
        "DESCRIPTION": "造成 !D! 点伤害。"
    },
    "mysteryDungeon:PikachuThunder": {
        "NAME": "打雷",
        "DESCRIPTION": "每当你激发一个充能球， 对所有敌人造成 !M! 点伤害。"
    },
    "mysteryDungeon:PikachuThunderbolt": {
        "NAME": "十万伏特",
        "DESCRIPTION": "造成 !D! 点伤害X次。 NL 如果最后一张牌是技能牌，获得 [E] 。"
    },
    "mysteryDungeon:PikachuThunderPunch": {
        "NAME": "雷电掌",
        "DESCRIPTION": "造成 !D! 点伤害。 NL 生成 !M! 个闪电充能球。"
    },
    "mysteryDungeon:PikachuThundershock": {
        "NAME": "电击",
        "DESCRIPTION": "造成 !D! 点伤害。 NL 如果你未处于姿态，获得 [E] 。"
    },
    "mysteryDungeon:PikachuThunderwave": {
        "NAME": "电磁波",
        "DESCRIPTION": "获得 !B! 点 格挡 。 NL 如果你未处于姿态，额外获得 !M! 点 格挡 。",
        "UPGRADE_DESCRIPTION": " mysterydungeon:惰性 。 NL 获得 !B! 点 格挡 。 NL 如果你未处于姿态，额外获得 !M! 点 格挡 。"
    },
    "mysteryDungeon:PikachuVoltSwitch": {
        "NAME": "伏特替换",
        "DESCRIPTION": " mysterydungeon:惰性 。 NL 保留。 NL 从 mysterydungeon:正极态 或 mysterydungeon:负极态 选择进入一种姿态。 NL 消耗。",
        "UPGRADE_DESCRIPTION": " mysterydungeon:惰性 。 NL 保留。 NL 从 mysterydungeon:正极态 或 mysterydungeon:负极态 选择进入一种姿态。"
    },
    "mysteryDungeon:PikachuVoltTackle": {
        "NAME": "伏特攻击",
        "DESCRIPTION": "固有。 NL 造成 !D! 点伤害。 NL 生成 !M! 个闪电充能球。 NL 消耗。"
    },
    "mysteryDungeon:PikachuWildCharge": {
        "NAME": "疯狂伏特",
        "DESCRIPTION": " mysterydungeon:惰性 。 NL 激发所有充能球2次。",
        "UPGRADE_DESCRIPTION": "激发所有充能球2次。"
    },
    "mysteryDungeon:PikachuZapCannon": {
        "NAME": "电磁炮",
        "DESCRIPTION": "每有一个敌人生成一个闪电充能球。 NL 对所有敌人造成 !D! 点伤害。 NL 消耗。"
    },
    "mysteryDungeon:SquirtleAquaRing": {
        "NAME": "水流环",
        "DESCRIPTION": "丢弃手牌中 !M! 张牌。 NL 每丢弃一张牌，置入一张挠。",
        "UPGRADE_DESCRIPTION": "丢弃手牌中 !M! 张牌。 NL 每丢弃一张牌，置入一张挠+。"
    },
    "mysteryDungeon:SquirtleAquaTail": {
        "NAME": "水流尾",
        "DESCRIPTION": "造成 !D! 点伤害。 NL 预见 !M! 张牌。 NL 抽取 !mysteryDungeon:M2! 张牌。 NL 丢弃 !mysteryDungeon:M3! 张牌。",
        "UPGRADE_DESCRIPTION": "造成 !D! 点伤害。 NL 预见 !M! 张牌。 NL 抽取 !mysteryDungeon:M2! 张牌。 NL 丢弃 !mysteryDungeon:M3! 张牌。"
    },
    "mysteryDungeon:SquirtleBide": {
        "NAME": "忍耐",
        "DESCRIPTION": "获得 !B! 点 格挡 。 NL直至下回合，每受到一次攻击，获得 !M! 点临时力量。"
    },
    "mysteryDungeon:SquirtleBodyPress": {
        "NAME": "扑击",
        "DESCRIPTION": "获得 !B! 点 格挡 。 NL 添加 !M! 张挠至手牌，本回合耗能为0。",
        "UPGRADE_DESCRIPTION": "获得 !B! 点 格挡 。 NL 添加 !M! 张挠+至手牌，本回合耗能为0。"
    },
    "mysteryDungeon:SquirtleBrine": {
        "NAME": "盐水",
        "DESCRIPTION": "造成 !D! 点伤害。 若抽牌堆牌数大于等于弃牌堆，造成 !D! 点伤害。"
    },
    "mysteryDungeon:SquirtleDefend": {
        "NAME": "防御",
        "DESCRIPTION": "获得 !B! 点 格挡 。"
    },
    "mysteryDungeon:SquirtleDive": {
        "NAME": "潜水",
        "DESCRIPTION": "清除全部状态。 NL 向抽牌堆或弃牌堆随机添加 !M! 张黑雾。 NL 消耗。"
    },
    "mysteryDungeon:SquirtleDoubleTeam": {
        "NAME": "影子分身",
        "DESCRIPTION": "获得 !B! 点 格挡 。 抽到该牌时:向手牌添加一张复制品。 NL 消耗。"
    },
    "mysteryDungeon:SquirtleEndure": {
        "NAME": "挺住",
        "DESCRIPTION": "当你打出一张状态牌，对所有敌人造成 !M! 点伤害。 NL 视为攻击伤害。"
    },
    "mysteryDungeon:SquirtleExplorerForm": {
        "NAME": "杰尼龟·冒险者笔记",
        "DESCRIPTION": "在你的回合开始时，再抽一张牌，增加此收益一层。",
        "UPGRADE_DESCRIPTION": "固有。 NL 在你的回合开始时，再抽一张牌，增加此收益一层。"
    },
    "mysteryDungeon:SquirtleFakeOut": {
        "NAME": "击掌奇袭",
        "DESCRIPTION": "固有。 NL 造成 !D! 点伤害。 NL 获得 !B! 点 格挡 。 NL 预见 !M! 张牌。 NL 消耗。",
        "UPGRADE_DESCRIPTION": "固有。 NL 造成 !D! 点伤害。 NL 获得 !B! 点 格挡 。 NL 预见 !M! 张牌。 NL 消耗。"
    },
    "mysteryDungeon:SquirtleFlashCannon": {
        "NAME": "加农光炮",
        "DESCRIPTION": "造成等同于你弃牌堆牌数量的伤害。",
        "UPGRADE_DESCRIPTION": "造成等同于你弃牌堆数量+3的伤害。",
        "EXTENDED_DESCRIPTION": [
            " NL (造成 !D! 点伤害。)"
        ]
    },
    "mysteryDungeon:SquirtleFlinch": {
        "NAME": "挠",
        "DESCRIPTION": "造成 !D! 点伤害2次。 NL 预见 !M! 张牌。 NL 消耗。",
        "UPGRADE_DESCRIPTION": "造成 !D! 点伤害2次。 NL 预见 !M! 张牌。 NL 消耗。"
    },
    "mysteryDungeon:SquirtleFlipTurn": {
        "NAME": "快速折返",
        "DESCRIPTION": "获得 !B! 点 格挡 。 NL 抽 !M! 张牌。 NL 丢弃 !M! 张牌。",
        "UPGRADE_DESCRIPTION": "获得 !B! 点 格挡 。 NL 抽 !M! 张牌。 NL 丢弃 !M! 张牌。"
    },
    "mysteryDungeon:SquirtleGyroBall": {
        "NAME": "陀螺球",
        "DESCRIPTION": "向手牌添加1张冷冻。 NL 手牌中每张状态牌造成 !D! 点伤害。 NL 丢弃手牌中所有状态牌。"
    },
    "mysteryDungeon:SquirtleHail": {
        "NAME": "冰雹",
        "DESCRIPTION": "每当你抽牌，对所有敌人造成 !M! 点伤害。"
    },
    "mysteryDungeon:SquirtleHaze": {
        "NAME": "黑雾",
        "DESCRIPTION": "获得 [E] [E] 。 NL 向弃牌堆添加 !M! 张冷冻。",
        "UPGRADE_DESCRIPTION": "获得 [E] [E] [E] 。 NL 向弃牌堆添加 !M! 张冷冻。"
    },
    "mysteryDungeon:SquirtleHydroCannon": {
        "NAME": "加农水炮",
        "DESCRIPTION": "对所有敌人造成 !D! 点伤害。 NL 将2张冷冻洗入抽牌堆。"
    },
    "mysteryDungeon:SquirtleIceBeam": {
        "NAME": "冰冻光束",
        "DESCRIPTION": "造成 !D! 点伤害。 NL 向手牌添加1张冷冻。"
    },
    "mysteryDungeon:SquirtleIronDefense": {
        "NAME": "铁壁",
        "DESCRIPTION": "获得 !M! 层敏捷。"
    },
    "mysteryDungeon:SquirtleLifeDew": {
        "NAME": "生命水滴",
        "DESCRIPTION": "预见 !M! 张牌。 NL 抽 !mysteryDungeon:M2! 张牌。"
    },
    "mysteryDungeon:SquirtleLiquidation": {
        "NAME": "水流裂破",
        "DESCRIPTION": "对所有敌人造成 !D! 点伤害。"
    },
    "mysteryDungeon:SquirtleMirrorCoat": {
        "NAME": "镜面反射",
        "DESCRIPTION": "获得 !M! 层 残影 和 !B! 点 格挡 。"
    },
    "mysteryDungeon:SquirtleMist": {
        "NAME": "白雾",
        "DESCRIPTION": "获得 !B! 点 格挡 。 NL 获得 !M! 层人工制品。 "
    },
    "mysteryDungeon:SquirtleProtect": {
        "NAME": "守住",
        "DESCRIPTION": "获得 !B! 点 格挡 。 NL 下 !M! 回合你不能获得 格挡 。"
    },
    "mysteryDungeon:SquirtleRainDance": {
        "NAME": "求雨",
        "DESCRIPTION": "本回合每制作一张牌，获得 !M! 点临时力量。",
        "UPGRADE_DESCRIPTION": "固有。 NL 本回合每制作一张牌，获得 !M! 点临时力量。"
    },
    "mysteryDungeon:SquirtleRainDish": {
        "NAME": "雨盘",
        "DESCRIPTION": "每当一张牌被手动预见或丢弃时，获得 !M! 点 格挡 。",
        "UPGRADE_DESCRIPTION": "固有。 NL 每当一张牌被手动预见或丢弃时，获得 !M! 点 格挡 。"
    },
    "mysteryDungeon:SquirtleRapidSpin": {
        "NAME": "高速旋转",
        "DESCRIPTION": "造成 !D! 点伤害。 NL 若敌人意图为攻击，获得 !M! 层人工制品。"
    },
    "mysteryDungeon:SquirtleScald": {
        "NAME": "热水",
        "DESCRIPTION": "丢弃 !mysteryDungeon:M2! 张牌，通过丢牌，造成 !D! 点伤害并施加 !M! 层 mysterydungeon:灼烧 。"
    },
    "mysteryDungeon:SquirtleShellSmash": {
        "NAME": "破壳",
        "DESCRIPTION": "获得 !M! 点力量。 NL 将 !mysteryDungeon:M2! 张冷冻洗入抽牌堆。"
    },
    "mysteryDungeon:SquirtleSkullBashGo": {
        "NAME": "火箭头锤",
        "DESCRIPTION": " 保留。 NL 对所有敌人造成 !D! 点伤害。 NL 如果该牌在手牌最左侧，对所有敌人造成 !D! 点伤害。 NL 消耗。",
        "UPGRADE_DESCRIPTION": "保留。 NL 对所有敌人造成 !D! 点伤害。 NL 如果该牌在手牌最左侧，对所有敌人造成 !D! 点伤害。 NL 消耗。"
    },
    "mysteryDungeon:SquirtleSkullBashReady": {
        "NAME": "火箭头锤: 准备!",
        "DESCRIPTION": "将一张火箭头锤洗入抽牌堆。",
        "UPGRADE_DESCRIPTION": "固有。 NL 将一张火箭头锤洗入抽牌堆。"
    },
    "mysteryDungeon:SquirtleSkullBashSet": {
        "NAME": "火箭头锤: 启动!",
        "DESCRIPTION": "虚无。 NL 添加一张火箭头锤至抽牌堆。 NL 消耗。",
        "UPGRADE_DESCRIPTION": "添加一张火箭头锤至抽牌堆。 NL 消耗。"
    },
    "mysteryDungeon:SquirtleSubstitute": {
        "NAME": "替身",
        "DESCRIPTION": "从抽牌堆选择一张牌。 NL 添加至你的手牌，并在该牌原位置置入一张伤口。 NL 消耗。",
        "UPGRADE_DESCRIPTION": "从抽牌堆选择一张牌。 NL 将该牌的复制品添加至你的手牌，并在该牌原位置置入一张伤口。 NL 消耗。"
    },
    "mysteryDungeon:SquirtleTackle": {
        "NAME": "杰尼攻击",
        "DESCRIPTION": "造成 !D! 点伤害。"
    },
    "mysteryDungeon:SquirtleTorrent": {
        "NAME": "暴雨",
        "DESCRIPTION": "当你洗牌时，获得 !M! 点临时力量。"
    },
    "mysteryDungeon:SquirtleWaterGun": {
        "NAME": "水枪",
        "DESCRIPTION": "造成 !D! 点伤害。 NL 预见 !M! 张牌。"
    },
    "mysteryDungeon:SquirtleWaterPulse": {
        "NAME": "水之波动",
        "DESCRIPTION": "造成 !D! 点伤害。 NL 施加 !M! 层易伤。"
    },
    "mysteryDungeon:SquirtleWaterSpout": {
        "NAME": "喷水",
        "DESCRIPTION": "预见 !M! 张牌。 NL 施加 !mysteryDungeon:M2! 层 虚弱 。 NL 造成 !D! 点伤害。",
        "UPGRADE_DESCRIPTION": "预见 !M! 张牌。 NL 施加 !mysteryDungeon:M2! 层 虚弱 。 NL 造成 !D! 点伤害。"
    },
    "mysteryDungeon:SquirtleWhirlpool": {
        "NAME": "潮旋",
        "DESCRIPTION": "下X回合开始时，额外抽2张牌并丢弃2张牌。 NL 消耗。",
        "UPGRADE_DESCRIPTION": "下X+1回合开始时，额外抽2张牌并丢弃2张牌。 NL 消耗。"
    },
    "mysteryDungeon:SquirtleWithdraw": {
        "NAME": "缩入壳中",
        "DESCRIPTION": "将弃牌堆洗入牌库 NL 手牌中每张牌获得 !M! 点 格挡 。"
    },
    "mysteryDungeon:SquirtleZenHeadbutt": {
        "NAME": "意念头锤",
        "DESCRIPTION": "造成 !D! 点伤害。 NL 向你的手牌加入一张挠。",
        "UPGRADE_DESCRIPTION": "造成 !D! 点伤害。 NL 向你的手牌加入一张挠。"
    },
    "mysteryDungeon:TotodileAquaJet": {
        "NAME": "Aqua Jet",
        "DESCRIPTION": "Innate. NL Deal !D! damage. Next turn gain !M! mysterydungeon:Vigor."
    },
    "mysteryDungeon:TotodileAquaTail": {
        "NAME": "Aqua Tail",
        "DESCRIPTION": "Deal !D! damage. NL Discard the top !M! cards from your draw pile.",
        "UPGRADE_DESCRIPTION": "Deal !D! damage. NL Scry !M!."
    },
    "mysteryDungeon:TotodileAvalanche": {
        "NAME": "Avalanche",
        "DESCRIPTION": "Whenever you activate an Orb, deal damage equal to your Block to a random enemy."
    },
    "mysteryDungeon:TotodileBite": {
        "NAME": "Bite",
        "DESCRIPTION": "Deal !D! damage."
    },
    "mysteryDungeon:TotodileBlizzard": {
        "NAME": "Blizzard",
        "DESCRIPTION": "Deal damage equal to !M! times the number of orbs channeled this combat.",
        "EXTENDED_DESCRIPTION": [
            "Deal damage equal to !M! times the number of orbs channneled this combat. NL (Currently deals !D! damage.)"
        ]
    },
    "mysteryDungeon:TotodileBlock": {
        "NAME": "Block",
        "DESCRIPTION": "Gain !B! Block. NL Channel !M! Frost."
    },
    "mysteryDungeon:TotodileChipAway": {
        "NAME": "Chip Away",
        "DESCRIPTION": "Deal !D! damage. NL Gain as much mysterydungeon:Vigor as you had before playing this card.",
        "UPGRADE_DESCRIPTION": "Deal !D! damage. NL Gain !M! more mysterydungeon:Vigor than you had before playing this card."
    },
    "mysteryDungeon:TotodileConfide": {
        "NAME": "Confide",
        "DESCRIPTION": "Apply !M! Vulnerable. NL Your next attack deals !mysteryDungeon:M2! additional damage. NL Exhaust."
    },
    "mysteryDungeon:TotodileCrunch": {
        "NAME": "Crunch",
        "DESCRIPTION": "Deal !D! damage. NL Choose a card from your discard pile and add it to the top of your draw pile."
    },
    "mysteryDungeon:TotodileDefend": {
        "NAME": "Defend",
        "DESCRIPTION": "Gain !B! Block."
    },
    "mysteryDungeon:TotodileDive": {
        "NAME": "Dive",
        "DESCRIPTION": "Retain. NL Discard !M! cards from your hand.",
        "UPGRADE_DESCRIPTION": "Retain. NL Discard !M! cards from your hand. NL Draw 1 card."
    },
    "mysteryDungeon:TotodileDoubleTeam": {
        "NAME": "Double Team",
        "DESCRIPTION": "mysterydungeon:Inert. NL Channel !M! Frost.",
        "UPGRADE_DESCRIPTION": "Innate. NL mysterydungeon:Inert. NL Channel !M! Frost."
    },
    "mysteryDungeon:TotodileEndure": {
        "NAME": "Endure",
        "DESCRIPTION": "If you take damage, channel !M! Frost.",
        "UPGRADE_DESCRIPTION": "Innate. NL If you take damage, channel !M! Frost."
    },
    "mysteryDungeon:TotodileExplorerForm": {
        "NAME": "Explorer Form",
        "DESCRIPTION": "Ethereal. NL At the start of your turn, add !M! card from your discard pile to your hand. NL Draw one less card per turn.",
        "UPGRADE_DESCRIPTION": "At the start of your turn, add !M! card from your discard pile to your hand. NL Draw one less card per turn."
    },
    "mysteryDungeon:TotodileHail": {
        "NAME": "Hail",
        "DESCRIPTION": "Unplayable. NL When discarded: Channel !M! Frost.",
        "UPGRADE_DESCRIPTION": "Unplayable. NL mysterydungeon:Scoop-up. NL When discarded: Channel !M! Frost.",
        "EXTENDED_DESCRIPTION": [
            "I can't play this card."
        ]
    },
    "mysteryDungeon:TotodileHydroCannon": {
        "NAME": "Hydro Cannon",
        "DESCRIPTION": "Costs 1 less [E] for each card discarded this turn. Deal !D! damage."
    },
    "mysteryDungeon:TotodileHydroPump": {
        "NAME": "Hydro Pump",
        "DESCRIPTION": "Can only be used if there are no cards left in your draw pile. NL Deal !D! damage.",
        "UPGRADE_DESCRIPTION": "Can only be used if there are !M! cards or less in your draw pile. NL Deal !D! damage."
    },
    "mysteryDungeon:TotodileIceBeam": {
        "NAME": "Ice Beam",
        "DESCRIPTION": "Deal !D! damage. NL Channel !M! Frost."
    },
    "mysteryDungeon:TotodileIceFang": {
        "NAME": "Ice Fang",
        "DESCRIPTION": "Deal !D! damage. NL Channel !M! Frost orb.",
        "UPGRADE_DESCRIPTION": "Innate. NL Deal !D! damage. NL Channel !M! Frost."
    },
    "mysteryDungeon:TotodileIcePunch": {
        "NAME": "Ice Punch",
        "DESCRIPTION": "Deal !D! damage. NL Channel !M! Frost. NL Evoke !M! Orb."
    },
    "mysteryDungeon:TotodileIcyWind": {
        "NAME": "Icy Wind",
        "DESCRIPTION": "mysterydungeon:Inert. NL Channel !M! Frost. NL Exhaust."
    },
    "mysteryDungeon:TotodileLiquidation": {
        "NAME": "Liquidation",
        "DESCRIPTION": "Deal !D! damage to ALL enemies."
    },
    "mysteryDungeon:TotodileScratch": {
        "NAME": "Scratch",
        "DESCRIPTION": "Deal !D! damage."
    },
    "mysteryDungeon:TotodileSheerForce": {
        "NAME": "Sheer Force",
        "DESCRIPTION": "Whenever you deal !M! or more unblocked damage, channel 1 Frost."
    },
    "mysteryDungeon:TotodileStrength": {
        "NAME": "Strength",
        "DESCRIPTION": "Draw !M! card. NL If you drew an Attack, channel 1 Frost orb."
    },
    "mysteryDungeon:TotodileSurf": {
        "NAME": "Surf",
        "DESCRIPTION": "Whenever you discard a card, gain !M! mysterydungeon:Temporary_Vigor."
    },
    "mysteryDungeon:TotodileSubstitute": {
        "NAME": "Substitute",
        "DESCRIPTION": "Gain !B! block. NL Gain !M! mysterydungeon:Vigor. NL End Your Turn."
    },
    "mysteryDungeon:TotodileRage": {
        "NAME": "Rage",
        "DESCRIPTION": "At the start of the next X turn, gain !M! mysterydungeon:Vigor. NL Exhaust.",
        "UPGRADE_DESCRIPTION": "At the start of the next X+1 turn, gain !M! mysterydungeon:Vigor. NL Exhaust."
    },
    "mysteryDungeon:TotodileRainDance": {
        "NAME": "Rain Dance",
        "DESCRIPTION": "Unplayable. NL When discarded: Your next Attack deals !M! additional damage.",
        "UPGRADE_DESCRIPTION": "Unplayable. NL mysterydungeon:Scoop-up NL When discarded: Your next Attack deals !M! additional damage.",
        "EXTENDED_DESCRIPTION": [
            "I can't play this card."
        ]
    },
    "mysteryDungeon:TotodileThrash": {
        "NAME": "Thrash",
        "DESCRIPTION": "Every !mysteryDungeon:M2! Attack you play, gain !M! mysterydungeon:Vigor."
    },
    "mysteryDungeon:TotodileTorrent": {
        "NAME": "Torrent",
        "DESCRIPTION": "Unplayable. NL When discarded: Gain !M! Focus.",
        "UPGRADE_DESCRIPTION": "Unplayable. NL mysterydungeon:Scoop-up NL When discarded: Gain !M! Focus.",
        "EXTENDED_DESCRIPTION": [
            "I can't play this card."
        ]
    },
    "mysteryDungeon:TotodileWaterfall": {
        "NAME": "Waterfall",
        "DESCRIPTION": "At the end of your turn shuffle your draw pile. NL At the start of your turn Scry !M!."
    },
    "mysteryDungeon:TotodileWaterGun": {
        "NAME": "Water Gun",
        "DESCRIPTION": "Discard the !M! top cards of your draw pile. NL Deal !D! damage."
    },
    "mysteryDungeon:TotodileWaterPledge": {
        "NAME": "Water Pledge",
        "DESCRIPTION": "Channel !M! Frost orb. NL If you play another mysterydungeon:Pledge card this turn, activate a special effect."
    },
    "mysteryDungeon:TotodileWaterPulse": {
        "NAME": "Water Pulse",
        "DESCRIPTION": "Discard the top !M! cards of your draw pile. For each card discarded this way, deal !D! damage."
    },
    "mysteryDungeon:TotodileWaterSport": {
        "NAME": "Water Sport",
        "DESCRIPTION": "Discard the top card of your draw pile. NL Gain !mysteryDungeon:M2! mysterydungeon:Vigor.",
        "UPGRADE_DESCRIPTION": "Discard the top 2 cards of your draw pile. NL Gain !mysteryDungeon:M2! mysterydungeon:Vigor."
    },
    "mysteryDungeon:TotodileWhirlpool": {
        "NAME": "Whirlpool",
        "DESCRIPTION": "Discard the top !M! card of your draw pile. NL Gain !mysteryDungeon:M2! Focus."
    },
    "mysteryDungeon:TotodileWorkUp": {
        "NAME": "Work Up",
        "DESCRIPTION": "If you do not have any empty Orb Slots, Gain !M! Orb Slots."
    }
}