{
    "mysteryDungeon:NegativeStance": {
        "NAME": "Négativité",
        "DESCRIPTION": [
            "Quand vous jouez une compétence, gagnez 1 Concentration temporaire. NL Quand vous quittez cette position, activez votre prochain Orbe 2 fois."
        ]
    },
    "mysteryDungeon:PositiveStance": {
        "NAME": "Positivité",
        "DESCRIPTION": [
            "Quand vous jouez une attaque, canalisez 1 Orbe de foudre. NL Quand vous quittez cette position, gagnez 7 d'Armure."
        ]
    }
}