{
    "mysteryDungeon:AspearBerryPotion": {
        "NAME": "Baie Willia",
        "DESCRIPTIONS": [
            "Défaussez autant de cartes de votre main que vous le souhaitez. Pigez #b%s cartes."
        ]
    },
    "mysteryDungeon:AuxPowerGuardPotion": {
        "NAME": "Double Extra",
        "DESCRIPTIONS": [
            "Gagnez #b%s de #yConcentration."
        ]
    },
    "mysteryDungeon:BerryJuicePotion": {
        "NAME": "Berry Juice",
        "DESCRIPTIONS": [
            "Scry #b%s. Next turn draw #b2 more cards.",
            "Scry #b%s. Next turn draw #b4 more cards."
        ]
    },
    "mysteryDungeon:DireHitPotion": {
        "NAME": "Muscle +",
        "DESCRIPTIONS": [
            "Votre prochaine attaque infligera le double des dégâts."
        ]
    },
    "mysteryDungeon:ElixirPotion": {
        "NAME": "Élixir",
        "DESCRIPTIONS": [
            "Gagnez [E] [E] [E] . Ajoutez #b2 #yBrûlures à votre main.",
            "Gagnez [E] [E] [E] [E] [E] [E] . Ajoutez #b4 #yBrûlures à votre main."
        ]
    },
    "mysteryDungeon:FlameOrbPotion": {
        "NAME": "Orbe Flamme",
        "DESCRIPTIONS": [
            "Appliquez #b%s de #Brûlure à TOUS les ennemis."
        ]
    },
    "mysteryDungeon:GoldenRazzBerryPotion": {
        "NAME": "Golden Razz Berry Potion",
        "DESCRIPTIONS": [
            "Gain #b%s #yBuffer."
        ]
    },
    "mysteryDungeon:AuxPowerPotion": {
        "NAME": "Offensive Extra",
        "DESCRIPTIONS": [
            "Votre prochaine attaque infligera #b%s dégâts supplémentaires."
        ]
    },
    "mysteryDungeon:HopoBerryPotion": {
        "NAME": "Hopo Berry",
        "DESCRIPTIONS": [
            "Choose between one random Attack or Skill card. Add it to your hand. It cost 0 this turn.",
            "Choose between one random Attack or Skill card. Add it to your hand. It cost 0 this turn."
        ]
    },
    "mysteryDungeon:LeppaBerryPotion": {
        "NAME": "Baie Mepo",
        "DESCRIPTIONS": [
            "Choisissez #b%s cartes à retenir à la fin de votre tour."
        ]
    },
    "mysteryDungeon:LiechiBerryPotion": {
        "NAME": "Liechi Berry",
        "DESCRIPTIONS": [
            "Draw #b%s cards.",
            "Draw #b%s cards."
        ]
    },
    "mysteryDungeon:MagoBerryPotion": {
        "NAME": "Baie Mago",
        "DESCRIPTIONS": [
            "Soignez #b%1$s PV. Appliquez-vous #b%2$s de #yPoison."
        ]
    },
    "mysteryDungeon:MeowthCandyPotion": {
        "NAME": "Bonbon Miaouss",
        "DESCRIPTIONS": [
            "Dépensez #b20 or. Appliquez les effets de #b2 #yPotions aléatoires."
        ]
    },
    "mysteryDungeon:NuggetPotion": {
        "NAME": "Pépite",
        "DESCRIPTIONS": [
            "Gagnez #b%s or."
        ]
    },
    "mysteryDungeon:PikachuCandyPotion": {
        "NAME": "Bonbon Pikachu",
        "DESCRIPTIONS": [
            "Entrez en #yPositivité ou en #yNégativité."
        ]
    },
    "mysteryDungeon:PinapBerryPotion": {
        "NAME": "Pinap Berry",
        "DESCRIPTIONS": [
            "Channel #b%s Frost orbs.",
            "Channel #b%s Frost orbs."
        ]
    },
    "mysteryDungeon:PoisonBarbPotion": {
        "NAME": "Pic Venin",
        "DESCRIPTIONS": [
            "Appliquez #b%s de Poison à un ennemi."
        ]
    },
    "mysteryDungeon:RawstBerryPotion": {
        "NAME": "Baie Fraive",
        "DESCRIPTIONS": [
            "Appliquez #b%s de #yBrûlure. La #yBrûlure de la cible ne diminuera pas pendant #b1 tour.",
            "Apply #b%s #yBurn. Burn stacks don't decrease for #b2 turns on the target."
        ]
    },
    "mysteryDungeon:SitrusBerryPotion": {
        "NAME": "Baie Sitrus",
        "DESCRIPTIONS": [
            "Ajoutez #b%s carte parmi vos cartes épuisées à votre main.",
            "Ajoutez #b%s cartes parmi vos cartes épuisées à votre main."
        ]
    },
    "mysteryDungeon:StarfBerryPotion": {
        "NAME": "Baie Frista",
        "DESCRIPTIONS": [
            "Gagnez #b%s de #yVigueur."
        ]
    },
    "mysteryDungeon:XAttackPotion": {
        "NAME": "Attaque +",
        "DESCRIPTIONS": [
            "Ajoutez #b%s #yPeur à votre main. Elles coûtent #b0 ce tour."
        ]
    },
    "mysteryDungeon:XSpAttackPotion": {
        "NAME": "Atq. Spé. +",
        "DESCRIPTIONS": [
            "Remplissez vos emplacements #yd'Orbes avec des #yOrbes #yKérauniques."
        ]
    }
}